NeuronOne/__init__.py
NeuronOne/perceptron.py
Neuron_one_pypi_misterak8-0.0.3.dist-info/LICENSE
Neuron_one_pypi_misterak8-0.0.3.dist-info/METADATA
Neuron_one_pypi_misterak8-0.0.3.dist-info/WHEEL
Neuron_one_pypi_misterak8-0.0.3.dist-info/top_level.txt
Neuron_one_pypi_misterak8-0.0.3.dist-info/RECORD
