Metadata-Version: 2.1
Name: Neuron-one-pypi-misterak8
Version: 0.0.3
Summary: its an implimentation of Perceptron
Home-page: https://github.com/misterak8/Neuron_one_pypi
Author: misterak8
Author-email: arjun.kopites@gmail.com
License: UNKNOWN
Project-URL: Bug Tracker, https://github.com/misterak8/Neuron_one_pypi/issues
Platform: UNKNOWN
Classifier: Programming Language :: Python :: 3
Classifier: License :: OSI Approved :: MIT License
Classifier: Operating System :: OS Independent
Requires-Python: >=3.7
License-File: LICENSE
Requires-Dist: numpy
Requires-Dist: tqdm
